skander_package_tutorial/__init__.py
skander_package_tutorial/string_ops.py
skander_package_tutorial-0.0.1.dist-info/METADATA
skander_package_tutorial-0.0.1.dist-info/WHEEL
skander_package_tutorial-0.0.1.dist-info/RECORD
