Metadata-Version: 2.4
Name: skander_package_tutorial
Version: 0.0.1
Summary: 
Author: skan652
Author-email: skander.afi@dauphine.tn
Requires-Python: >=3.14
Classifier: Programming Language :: Python :: 3
Classifier: Programming Language :: Python :: 3.14
Requires-Dist: pre-commit (>=4.5.1,<5.0.0)
Requires-Dist: pytest (>=9.0.2,<10.0.0)
Requires-Dist: pytest-cov (>=7.0.0,<8.0.0)
Requires-Dist: ruff (>=0.14.13,<0.15.0)
Requires-Dist: sphinx (>=9.1.0,<10.0.0)
Requires-Dist: sphinx-rtd-theme (>=3.1.0,<4.0.0)
